gammarers/aws_waf_geo_restriction_rule_group/__init__.py
gammarers/aws_waf_geo_restriction_rule_group/py.typed
gammarers/aws_waf_geo_restriction_rule_group/_jsii/__init__.py
gammarers/aws_waf_geo_restriction_rule_group/_jsii/aws-waf-geo-restriction-rule-group@1.5.18.jsii.tgz
gammarers.aws_waf_geo_restriction_rule_group-1.5.18.dist-info/LICENSE
gammarers.aws_waf_geo_restriction_rule_group-1.5.18.dist-info/METADATA
gammarers.aws_waf_geo_restriction_rule_group-1.5.18.dist-info/WHEEL
gammarers.aws_waf_geo_restriction_rule_group-1.5.18.dist-info/top_level.txt
gammarers.aws_waf_geo_restriction_rule_group-1.5.18.dist-info/RECORD
